snownlp/__init__.py
snownlp/classification/__init__.py
snownlp/classification/bayes.py
snownlp/normal/__init__.py
snownlp/normal/pinyin.py
snownlp/normal/zh.py
snownlp/seg/__init__.py
snownlp/seg/seg.py
snownlp/seg/y09_2047.py
snownlp/sentiment/__init__.py
snownlp/sim/__init__.py
snownlp/sim/bm25.py
snownlp/summary/__init__.py
snownlp/summary/textrank.py
snownlp/summary/words_merge.py
snownlp/tag/__init__.py
snownlp/utils/__init__.py
snownlp/utils/frequency.py
snownlp/utils/good_turing.py
snownlp/utils/tnt.py
snownlp/utils/trie.py
xy_words-0.1.dist-info/METADATA
xy_words-0.1.dist-info/WHEEL
xy_words-0.1.dist-info/top_level.txt
xy_words-0.1.dist-info/RECORD
