Metadata-Version: 2.1
Name: xy-words
Version: 0.1
Summary: 星圆文字处理，基于snowNlp与jieba
Home-page: UNKNOWN
Author: Xingyuan55
Author-email: dus0963@outlook.com
License: MPL
Platform: UNKNOWN
Requires: jieba
Requires: wheel
